invenio_checks/__init__.py
invenio_checks/api.py
invenio_checks/base.py
invenio_checks/components.py
invenio_checks/config.py
invenio_checks/ext.py
invenio_checks/models.py
invenio_checks/proxies.py
invenio_checks/utils.py
invenio_checks/alembic/1742548610_create_checks_branch.py
invenio_checks/alembic/1742549302_create_base_tables.py
invenio_checks/contrib/__init__.py
invenio_checks/contrib/file_formats.py
invenio_checks/contrib/metadata/__init__.py
invenio_checks/contrib/metadata/check.py
invenio_checks/contrib/metadata/expressions.py
invenio_checks/contrib/metadata/rules.py
invenio_checks/services/__init__.py
invenio_checks/services/config.py
invenio_checks/services/permissions.py
invenio_checks/services/results.py
invenio_checks/services/schema.py
invenio_checks/services/services.py
invenio_checks/templates/semantic-ui/invenio_checks/requests/details.html
invenio_checks/templates/semantic-ui/invenio_checks/requests/file_formats_tab.html
invenio_checks/templates/semantic-ui/invenio_checks/requests/help_message.html
invenio_checks/templates/semantic-ui/invenio_checks/requests/metadata_tab.html
invenio_checks/templates/semantic-ui/invenio_checks/requests/overall_severity_level.html
invenio_checks/templates/semantic-ui/invenio_checks/requests/severity_level_icons.html
invenio_checks/views/__init__.py
invenio_checks/views/ui.py
invenio_checks-3.0.0.dist-info/licenses/AUTHORS.rst
invenio_checks-3.0.0.dist-info/licenses/LICENSE
invenio_checks-3.0.0.dist-info/METADATA
invenio_checks-3.0.0.dist-info/WHEEL
invenio_checks-3.0.0.dist-info/entry_points.txt
invenio_checks-3.0.0.dist-info/top_level.txt
invenio_checks-3.0.0.dist-info/RECORD
