Metadata-Version: 2.4
Name: invenio-checks
Version: 3.0.0
Summary: Invenio module to automated curation checks on records.
Home-page: https://github.com/inveniosoftware/invenio-checks
Author: CERN
Author-email: info@inveniosoftware.org
License: MIT
Keywords: invenio rdm checks
Platform: any
Classifier: Development Status :: 1 - Planning
Requires-Python: >=3.9
License-File: LICENSE
License-File: AUTHORS.rst
Requires-Dist: invenio-base<3.0.0,>=2.3.0
Requires-Dist: invenio-i18n<4.0.0,>=3.0.0
Requires-Dist: invenio-communities<23.0.0,>=22.0.0
Requires-Dist: invenio-drafts-resources<8.0.0,>=7.0.0
Provides-Extra: tests
Requires-Dist: invenio-app<3.0.0,>=2.0.0; extra == "tests"
Requires-Dist: invenio-db[mysql,postgresql]<3.0.0,>=2.0.0; extra == "tests"
Requires-Dist: pytest-invenio<4.0.0,>=3.0.0; extra == "tests"
Requires-Dist: pytest-black>=0.4.0; extra == "tests"
Requires-Dist: sphinx>=4.5.0; extra == "tests"
Provides-Extra: opensearch1
Requires-Dist: invenio-search[opensearch1]<4.0.0,>=3.0.0; extra == "opensearch1"
Provides-Extra: opensearch2
Requires-Dist: invenio-search[opensearch2]<4.0.0,>=3.0.0; extra == "opensearch2"
Dynamic: license-file
